pkmodel/__init__.py
pkmodel/model.py
pkmodel/protocol.py
pkmodel/solution.py
pkmodel/version_info.py
pkmodel/tests/__init__.py
pkmodel/tests/test_model.py
pkmodel/tests/test_pipeline.py
pkmodel/tests/test_protocol.py
pkmodel/tests/test_solution.py
dtp_pkmodel-1.0.0.dist-info/LICENSE
dtp_pkmodel-1.0.0.dist-info/METADATA
dtp_pkmodel-1.0.0.dist-info/WHEEL
dtp_pkmodel-1.0.0.dist-info/top_level.txt
dtp_pkmodel-1.0.0.dist-info/RECORD
