Metadata-Version: 2.1
Name: dtp-pkmodel
Version: 1.0.0
Summary: An example Python project.
Home-page: https://github.com/SABS-R3/2020-software-engineering-projects-pk
Maintainer: Martin Robinson
Maintainer-email: martin.robinson@cs.ox.ac.uk
License: MIT license
Platform: UNKNOWN
Requires-Dist: numpy (>=1.19.2)
Requires-Dist: matplotlib (>=3.3.2)
Requires-Dist: scipy (>=1.5.3)
Provides-Extra: dev
Requires-Dist: flake8 (>=3) ; extra == 'dev'
Provides-Extra: docs
Requires-Dist: sphinx (!=1.7.3,>=1.5) ; extra == 'docs'
Requires-Dist: sphinx-rtd-theme ; extra == 'docs'
